ferpy/__init__.py
ferpy/auxiliary/__init__.py
ferpy/auxiliary/changelog_entry.py
ferpy/auxiliary/correlations.py
ferpy/auxiliary/coverage.py
ferpy/auxiliary/probability_density_function.py
ferpy/auxiliary/state.py
ferpy/main/__init__.py
ferpy/main/measurement.py
ferpy/main/quantity_values.py
ferpy/main/source.py
ferpy-0.1.16.dist-info/licenses/LICENSE
ferpy-0.1.16.dist-info/METADATA
ferpy-0.1.16.dist-info/WHEEL
ferpy-0.1.16.dist-info/top_level.txt
ferpy-0.1.16.dist-info/RECORD
